{
  "id": 37,
  "name": "Bab 2: Rute Lanjutan 12",
  "description": "Tantangan bab Bab 2: Rute Lanjutan.",
  "width": 10,
  "height": 8,
  "movesLimit": 23,
  "initialRules": {
    "red": "STOP",
    "blue": "STOP",
    "green": "STOP"
  },
  "allowedRules": {
    "red": [
      "STOP",
      "PUSH"
    ],
    "blue": [
      "STOP",
      "SWAP"
    ],
    "green": [
      "STOP",
      "MERGE"
    ]
  },
  "map": [
    "##########",
    "#@.......#",
    "#........#",
    "#........#",
    "#........#",
    "#........#",
    "#.......X#",
    "##########"
  ]
}
